monitescript/__init__.py
monitescript/monite.py
monitescript/token_transformers.py
monitescript/util.py
monitescript-0.6.0.dist-info/entry_points.txt
monitescript-0.6.0.dist-info/WHEEL
monitescript-0.6.0.dist-info/METADATA
monitescript-0.6.0.dist-info/RECORD
