Metadata-Version: 2.1
Name: monitescript
Version: 0.6.0
Summary: 
Keywords: python,shell,bash,script,scripting,monitescript
Author: Stanislav Zmiev
Author-email: szmiev2000@gmail.com
Requires-Python: >=3.7,<4.0
Classifier: Operating System :: OS Independent
Classifier: Programming Language :: Python :: 3
Classifier: Programming Language :: Python :: 3.7
Classifier: Programming Language :: Python :: 3.8
Classifier: Programming Language :: Python :: 3.9
Classifier: Programming Language :: Python :: 3.10
Classifier: Programming Language :: Python :: 3.11
Classifier: Topic :: Software Development :: Libraries :: Python Modules
Classifier: Topic :: System :: Shells
Classifier: Topic :: Utilities
Requires-Dist: ideas (>=0.0.37,<0.0.38)
Requires-Dist: tomlkit (>=0.10.0,<0.11.0)
Requires-Dist: typer[all] (>=0.4.0,<0.5.0)
Requires-Dist: typing-extensions (>=4.2.0,<5.0.0)
